labelutils/__init__.py
labelutils/_char_indices.py
labelutils/_conversions.py
labelutils/_inception.py
labelutils/_labelbuddy.py
labelutils/_utils.py
labelutils-0.0.1.dist-info/COPYING
labelutils-0.0.1.dist-info/METADATA
labelutils-0.0.1.dist-info/WHEEL
labelutils-0.0.1.dist-info/entry_points.txt
labelutils-0.0.1.dist-info/top_level.txt
labelutils-0.0.1.dist-info/RECORD
