Metadata-Version: 2.1
Name: labelutils
Version: 0.0.1
Summary: Conversions between labelbuddy json and other formats.
Author: Jérôme Dockès
Author-email: jerome@dockes.org
Maintainer: Jérôme Dockès
Maintainer-email: jerome@dockes.org
License: MIT License
Classifier: License :: OSI Approved :: MIT License
Classifier: Programming Language :: Python :: 3
License-File: COPYING
Requires-Dist: numpy
Requires-Dist: pandas
